dbt_argo/__init__.py
dbt_argo/argo/__init__.py
dbt_argo/argo/arguments.py
dbt_argo/argo/base.py
dbt_argo/argo/container.py
dbt_argo/argo/cron_workflow.py
dbt_argo/argo/cron_workflow_spec.py
dbt_argo/argo/dag_task.py
dbt_argo/argo/dag_template.py
dbt_argo/argo/envvar.py
dbt_argo/argo/inputs.py
dbt_argo/argo/metadata.py
dbt_argo/argo/parameter.py
dbt_argo/argo/quantity.py
dbt_argo/argo/resources.py
dbt_argo/argo/template.py
dbt_argo/argo/workflow.py
dbt_argo/argo/workflow_spec.py
dbt_argo/argo/workflow_step.py
dbt_argo/cli.py
dbt_argo/dbt/__init__.py
dbt_argo/dbt/columns.py
dbt_argo/dbt/config.py
dbt_argo/dbt/manifest.py
dbt_argo/dbt/node.py
dbt_argo/dbt_workflow.py
dbt_argo/main.py
dbt_argo/utils.py
dbt_argo-0.1.0rc0.dist-info/LICENSE
dbt_argo-0.1.0rc0.dist-info/METADATA
dbt_argo-0.1.0rc0.dist-info/WHEEL
dbt_argo-0.1.0rc0.dist-info/entry_points.txt
dbt_argo-0.1.0rc0.dist-info/RECORD
