Metadata-Version: 2.1
Name: dbt-argo
Version: 0.1.0rc0
Summary: A dbt pipeline converter to Argo Workflows
Author: Léo Grosjean
Author-email: leo.grosjean@live.fr
Requires-Python: >=3.9,<4.0
Classifier: Programming Language :: Python :: 3
Classifier: Programming Language :: Python :: 3.9
Classifier: Programming Language :: Python :: 3.10
Classifier: Programming Language :: Python :: 3.11
Requires-Dist: PyYAML (>=6.0.1,<7.0.0)
Requires-Dist: click (>=8.1.6,<9.0.0)
Requires-Dist: pydantic (>=2.1.1,<3.0.0)
